Workbook

Sheet Risk Method
B1: 8.1 Risk assessment method
B4: Scale | C4: Low (1) | D4: Medium (2) | E4: High (3)
B5: Probability | C5: No current indicator. Occurrence would require an unexpected change in project or organisational conditions before the M4 gate. | D5: Plausible on the evidence available, or dependent on an assumption the team has recorded but not confirmed. | E5: An indicator is already present in the scenario or the project, or the risk depends on information the team knows it does not have.
B6: Impact | C6: Absorbed within the current milestone. No baselined requirement, constraint or date changes. | D6: Forces a controlled change to a baselined artefact, or consumes schedule contingency, or degrades a stated business capability. | E6: Defeats a stated business need or a committed capability, breaches a security or personal-information obligation, or threatens the milestone gate. Recovery requires re-baselining.
B8: Priority bands
B9: 1 – 2 | C9: LOW — monitored at the scheduled milestone review; no action committed.
B10: 3 – 4 | C10: MEDIUM — a named mitigation is committed and tracked to a milestone.
B11: 6 – 9 | C11: HIGH — mitigation is active now and the risk is reviewed at every team meeting.
B13: The register is reviewed at every milestone, as required by Master Project Brief s.12.
B15: Numeric scale used in the Prob. and Impact columns — enter 1, 2 or 3
B16: Low | C16: 1
B17: Medium | C17: 2
B18: High | C18: 3
B20: Risk exposure matrix
B21: Each cell is the Priority score the scale produces for that combination — Probability × Impact. Colour shows the band: 1–2 Low, 3–4 Medium, 6–9 High.
B23: Impact ↓ / Probability → | C23: Low (1) | D23: Medium (2) | E23: High (3)
B24: High (3) | C24: 3 | D24: 6 | E24: 9
B25: Medium (2) | C25: 2 | D25: 4 | E25: 6
B26: Low (1) | C26: 1 | D26: 2 | E26: 3
B29: Where the register’s risks actually are (open, re-scored and new; closed and materialised rows are excluded below)
B30: Impact ↓ / Probability → | C30: Low (1) | D30: Medium (2) | E30: High (3)
B31: High (3) | C31: =COUNTIFS('Risk Register'!$F$3:$F$30,1,'Risk Register'!$G$3:$G$30,3,'Risk Register'!$M$3:$M$30,"Open*") | D31: =COUNTIFS('Risk Register'!$F$3:$F$30,2,'Risk Register'!$G$3:$G$30,3,'Risk Register'!$M$3:$M$30,"Open*") | E31: =COUNTIFS('Risk Register'!$F$3:$F$30,3,'Risk Register'!$G$3:$G$30,3,'Risk Register'!$M$3:$M$30,"Open*")
B32: Medium (2) | C32: =COUNTIFS('Risk Register'!$F$3:$F$30,1,'Risk Register'!$G$3:$G$30,2,'Risk Register'!$M$3:$M$30,"Open*") | D32: =COUNTIFS('Risk Register'!$F$3:$F$30,2,'Risk Register'!$G$3:$G$30,2,'Risk Register'!$M$3:$M$30,"Open*") | E32: =COUNTIFS('Risk Register'!$F$3:$F$30,3,'Risk Register'!$G$3:$G$30,2,'Risk Register'!$M$3:$M$30,"Open*")
B33: Low (1) | C33: =COUNTIFS('Risk Register'!$F$3:$F$30,1,'Risk Register'!$G$3:$G$30,1,'Risk Register'!$M$3:$M$30,"Open*") | D33: =COUNTIFS('Risk Register'!$F$3:$F$30,2,'Risk Register'!$G$3:$G$30,1,'Risk Register'!$M$3:$M$30,"Open*") | E33: =COUNTIFS('Risk Register'!$F$3:$F$30,3,'Risk Register'!$G$3:$G$30,1,'Risk Register'!$M$3:$M$30,"Open*")
B36: Band | C36: Count
B37: High | C37: =COUNTIFS('Risk Register'!$I$3:$I$30,"High",'Risk Register'!$M$3:$M$30,"Open*")
B38: Medium | C38: =COUNTIFS('Risk Register'!$I$3:$I$30,"Medium",'Risk Register'!$M$3:$M$30,"Open*")
B39: Low | C39: =COUNTIFS('Risk Register'!$I$3:$I$30,"Low",'Risk Register'!$M$3:$M$30,"Open*")
B40: Total | C40: =SUM(C37:C39)
B41: Closed or materialised | C41: =COUNTA('Risk Register'!$B$3:$B$30)-C40

Sheet Risk Register
B1: 8.2 Risk Register
B2: ID | C2: Risk description | D2: Cause | E2: Early-warning indicator | F2: Prob. (1–3) | G2: Impact (1–3) | H2: Priority (P×I) | I2: Band | J2: Mitigation (preventive) | K2: Contingency (if realised) | L2: Owner | M2: Status | N2: Linked artefacts | O2: M2 review — 30/09/2026 (what changed and why)
B3: RSK-001 | C3: Requesters keep using email, telephone and WhatsApp after the platform is live, so the single controlled record of a request lifecycle is never achieved. | D3: SCP-017 deliberately excludes ingestion from the existing channels, and nothing in the platform closes them. Channel retirement is an organisational decision the team does not control. | E3: Any pilot week in which STK-004 reports requests still arriving by telephone or WhatsApp. | F3: 3 | G3: 3 | H3: =F3*G3 | I3: =IF($H3="","",IF($H3>=6,"High",IF($H3>=3,"Medium","Low"))) | J3: The exclusion in SCP-017 is defended on the correct engineering ground — federating the old channels would preserve the duplication the platform exists to remove — so the residual exposure is adoption, not design. Record channel retirement as an assumption with its impact if invalid and raise it with STK-008 and STK-004 as an organisational commitment rather than a system feature. Ensure SCP-001 supports STK-004 capturing a request on a requester's behalf, so contacts that still arrive informally enter the controlled record. | K3: Coordinator-side capture becomes the primary path rather than the exception; record the reduced value against STK-001 and the weakened reporting against STK-005. | L3: Ethan | M3: Open | N3: SCP-017 · SCP-001 · STK-001 · STK-004 · STK-008 · FEC-002 | O3: Reviewed at M2 — no change.
B4: RSK-002 | C4: Identifiable personal information is retained indefinitely because no retention period exists and automated enforcement is deferred. | D4: DEC-005 defers the retention period pending guidance from STK-009 that the team does not have, and SCP-020 defers enforcement as a consequence. With no rule, the default behaviour of any implementation is to keep everything. | E4: A gap in the PROC-001 run log, or a closed request older than 30 days that still carries personal fields. | F4: 1 | G4: 3 | H4: =F4*G4 | I4: =IF($H4="","",IF($H4>=6,"High",IF($H4>=3,"Medium","Low"))) | J4: Keep DEC-005 open with a named owner and a target date, and pursue STK-009 as a tracked dependency rather than waiting for guidance to arrive. Require the M2 data model to separate identifiable request data from the aggregated statistics CFL-004 depends on, so a retention rule can later be applied without destroying the reporting STK-005 needs. | K4: Adopt a documented institutional retention standard as an interim position, recorded as an assumption with its basis, and mark the affected acceptance criteria provisional until STK-009 confirms. | L4: Ethan | M4: Open — re-scored at M2 | N4: DEC-005 · CFL-004 · SCP-020 · CON-007 · STK-009 · FEC-001 | O4: Re-scored: probability 3 → 1 (priority 9 → 3). The cause no longer holds: DEC-005 fixed the retention period and DEC-017 separates retention by purpose; PROC-001 enforces it by witnessed manual procedure. Residual: a missed PROC-001 run. Indicator changed to a gap in the PROC-001 run log. Proposed by R. van der Merwe (PED v1.7 §8.3.1), adopted by the register owner.
B5: RSK-003 | C5: 'Overdue' has no agreed definition, so SCP-011 cannot be specified, accepted or tested. | D5: SCP-011 commits to identifying overdue requests, but no service-level target exists for any category and — unlike every other open question in the baseline — no decision or deferment has been logged for it. | E5: An acceptance criterion for SCP-011 that a third party could not evaluate without asking the team what was meant. | F5: 3 | G5: 2 | H5: =F5*G5 | I5: =IF($H5="","",IF($H5>=6,"High",IF($H5>=3,"Medium","Low"))) | J5: Log the target as a decision now — either agreed with STK-005 or deferred with the evidence required stated — so it sits inside the decision log rather than outside it. Specify SCP-011 against a configurable target per category so the requirement survives whatever is later agreed. CON-005 requires the resulting quality attribute to carry a number and a condition. | K5: Baseline a stated default target, record it as an assumption with its basis, and mark the SCP-011 acceptance criteria provisional. | L5: Robert | M5: Open | N5: SCP-011 · STK-005 · CON-005 · no DEC logged — gap | O5: Reviewed at M2 — no change.
B6: RSK-004 | C6: Duplicate requests are recreated inside the platform, so the duplication STK-004 needs removed persists in a new form. | D6: Avoiding duplicate requests is STK-004's primary stated need, but no in-scope capability addresses detection. SCP-006 provides search and filter after the fact, not prevention at the point of submission. | E6: Demonstration or pilot data showing several open requests with the same category and location. | F6: 3 | G6: 2 | H6: =F6*G6 | I6: =IF($H6="","",IF($H6>=6,"High",IF($H6>=3,"Medium","Low"))) | J6: Raise a functional requirement for surfacing candidate duplicates by category and location at submission, traced to STK-004, with an acceptance measure expressed as coordinator triage effort rather than as a feature. If the team decides not to add it, record the omission as an accepted residual risk rather than leaving it implied by silence. | K6: Provide STK-004 with a link-or-merge action on related requests and accept the residual manual effort, recording it against that stakeholder. | L6: Robert | M6: Open | N6: STK-004 · SCP-001 · SCP-006 · Master Brief s.2 | O6: Reviewed at M2 — no change.
B7: RSK-005 | C7: Management reporting is unreliable because the detail it depends on is optional. | D7: DEC-006 limits mandatory capture to category, location and description and moves further detail to after submission. CFL-001 accepts that reporting richness therefore depends on requesters supplying optional detail they have little incentive to supply. | E7: Sample submissions in which the post-submission detail is left empty. | F7: 2 | G7: 2 | H7: =F7*G7 | I7: =IF($H7="","",IF($H7>=6,"High",IF($H7>=3,"Medium","Low"))) | J7: Specify post-submission prompting as a requirement rather than an assumed behaviour, and define a completeness measure for STK-005's reporting so DEC-006 can be evaluated against evidence rather than debated. A's decision already anticipates revisiting it through change control — give that trigger a number. | K7: Make one additional field mandatory through controlled change, accepting the submission-effort cost to STK-001 that CFL-001 was resolved to avoid. | L7: Robert | M7: Open | N7: DEC-006 · CFL-001 · SCP-011 · STK-001 · STK-005 | O7: Reviewed at M2 — no change.
B8: RSK-006 | C8: The campus context assumption proves wrong, invalidating the stakeholder register and every requirement derived from it. | D8: DEC-001 records that the Master Brief does not name the client organisation and that a campus context was inferred from the request types. The decision itself states that STK-001 to STK-009 and every derived requirement would have to be revisited. | E8: Any lecturer feedback that questions the client organisation rather than the analysis. | F8: 1 | G8: 3 | H8: =F8*G8 | I8: =IF($H8="","",IF($H8>=6,"High",IF($H8>=3,"Medium","Low"))) | J8: Confirm the context with the lecturer acting as proxy client at the earliest review point — the check costs nothing and removes the risk entirely. Until then keep the derivation visible in the RTM so the blast radius of a reversal is known rather than discovered. | K8: Rework the stakeholder register and re-derive requirements through controlled change with a full impact assessment; retain the identifiers and mark superseded entries Withdrawn rather than renumbering. | L8: Ethan | M8: Open | N8: DEC-001 · STK-001…STK-009 · CON-007 · RTM | O8: Reviewed at M2 — no change.
B9: RSK-007 | C9: The technology stack selected at M2 is unavailable or unsupported in the institutional environment. | D9: CON-008 records that Belgium Campus does not guarantee availability or support for any chosen language, framework, service or platform. DEC-002 defers the choice and names environment verification as evidence still required. | E9: M2 planning that names a stack before the availability check has been run. | F9: 1 | G9: 3 | H9: =F9*G9 | I9: =IF($H9="","",IF($H9>=6,"High",IF($H9>=3,"Medium","Low"))) | J9: Turn the availability check on the BC Desktop platform into a dated task with a named owner rather than an open evidence note, and run it before the M2 decision rather than alongside it. Keep candidate stacks inside CON-004 so that the fallback is genuinely usable by three part-time students. | K9: Fall back to a stack already proven available in the environment, accept the reduced requirement fit, and record the trade-off in the M2 ADR. | L9: Ethan | M9: Open — re-scored at M2 | N9: CON-008 · DEC-002 · CON-004 · FEC-004 | O9: Stack selected (DEC-002: MERN with MongoDB Atlas). The application builds and its test suite runs on Node 22 on team machines, and CI (#52) adds a hosted-runner build on every pull request. Probability reduced 2 → 1 (priority 6 → 3). Residual: a platform difference found only at deployment (DEC-003, RSK-019).
B10: RSK-008 | C10: The hosting platform cannot satisfy the security and personal-information constraints within the cost constraint. | D10: DEC-003 records that free tiers commonly omit audit log retention, backups and private networking, which CON-006 and CON-007 require. The conflict is documented but unresolved, and SCP-014 and SCP-015 both depend on it. | E10: A candidate platform shortlisted on price before its audit and backup limits are documented. | F10: 2 | G10: 3 | H10: =F10*G10 | I10: =IF($H10="","",IF($H10>=6,"High",IF($H10>=3,"Medium","Low"))) | J10: Make the free-tier limits research a dated deliverable before the M2 architecture is fixed, covering audit log retention, backup and likely operational cost beyond the educational context. Specify the audit requirement behind SCP-008 measurably now, so platforms can be assessed against a stated need rather than chosen and then justified. | K10: Accept a paid tier and record the operational cost against STK-008, or reduce the audit retention period through controlled change with STK-009 consulted. | L10: Ethan | M10: Closed — superseded by RSK-019, RSK-020 | N10: DEC-003 · CON-003 · CON-006 · CON-007 · SCP-008 · SCP-014 · SCP-015 · FEC-005 | O10: Closed at M2. The conflict it described is resolved by DEC-003 (Hostinger VPS, Atlas cluster per environment) and DEC-010 (operated 12-hourly backup). Its residual exposure is carried by RSK-019 (free-cluster ceilings) and RSK-020 (backup silently stops). Row retained; identifier not reused (PED §1.4).
B11: RSK-009 | C11: Role-based access control is specified but only partially delivered, so the CFL-002 restriction on security-category requests is not honoured. | D11: SCP-012 and DEC-004 correctly treat authorisation as architecturally significant, but it is realised at M2 and M3 across every view and status transition. Partially applied authorisation is indistinguishable from working software until the wrong person sees a security request. | E11: Any view or status transition specified without naming which role may reach it. | F11: 2 | G11: 3 | H11: =F11*G11 | I11: =IF($H11="","",IF($H11>=6,"High",IF($H11>=3,"Medium","Low"))) | J11: Specify the CFL-002 behaviour as testable acceptance criteria now — a requester on a security-category request sees only received, in progress and closed, and a staff member outside the security role cannot retrieve detail or comments — so it is verifiable at M3 rather than asserted. Make authorisation a required review dimension on every pull request touching a view or a transition. | K11: Restrict the security category to the security role entirely until the role model is verified, accepting the reduced requester visibility and recording it against STK-001. | L11: Robert | M11: Open | N11: CFL-002 · SCP-012 · DEC-004 · DEC-012 · CON-006 · STK-006 · STK-007 · FEC-001 · C-01 · OI-15 | O11: Unchanged score, now load-bearing. DEC-012 enforcement point 3 (field-level serialiser) rests on the CFL-002 resolution, still Proposed (condition C-01 open). PR #62 review B-1 found security-category requests could not be closed or rejected by anyone; fixed there by giving the Security Officer disposition rights, recorded for confirmation under OI-15.
B12: RSK-010 | C12: Quality thresholds baselined at M1 prove unachievable on the stack and platform chosen at M2. | D12: DEC-002 and DEC-003 both defer, while CON-005 requires quality attributes to be defined measurably now and evidenced later. The thresholds are therefore committed before anything is known about what will run them. | E12: A quality attribute whose threshold was chosen without a stated measurement condition. | F12: 2 | G12: 2 | H12: =F12*G12 | I12: =IF($H12="","",IF($H12>=6,"High",IF($H12>=3,"Medium","Low"))) | J12: State every quality attribute with its metric, threshold, condition and verification method, and keep thresholds evidence-based rather than aspirational. Make the M2 stack and platform decisions explicitly assessed against the baselined quality set rather than chosen first and reconciled afterwards. | K12: Relax a threshold only through controlled change with the impact and justification recorded — never by silent redefinition. | L12: Robert | M12: Open | N12: CON-005 · DEC-002 · DEC-003 · FEC-003 | O12: Reviewed at M2 — no change.
B13: RSK-011 | C13: Mobile web usability fails the technicians who must update status from where the work is done. | D13: DEC-007 excludes a native application and places a usability obligation on the web interface for mobile viewports. STK-002's stated need is to update status away from a desk, on institutional wireless coverage. | E13: A technician status-update path that has only been exercised on a desktop viewport. | F13: 2 | G13: 2 | H13: =F13*G13 | I13: =IF($H13="","",IF($H13>=6,"High",IF($H13>=3,"Medium","Low"))) | J13: Specify the mobile-viewport obligation DEC-007 creates as a measurable quality attribute with a device class and network condition, as CON-005 requires, rather than leaving it as a design intention. Make the status-transition path on a phone-sized viewport an acceptance criterion for SCP-008. | K13: Reduce the technician path to a minimal status-update view, accepting reduced functionality on mobile and recording it against STK-002 and STK-003. | L13: Robert | M13: Open | N13: DEC-007 · SCP-013 · SCP-008 · STK-002 · STK-003 · CON-005 | O13: Reviewed at M2 — no change.
B14: RSK-012 | C14: Traceability decays after baseline because merged changes do not update the RTM, breaking the source-to-acceptance chain. | D14: The RTM's design, test and release columns are only populated from M2 onward, so it is easy to merge a change and leave the matrix behind. CON-001 requires controlled change, which depends on the trace being current. | E14: A merged pull request that names no requirement or scope ID. | F14: 2 | G14: 3 | H14: =F14*G14 | I14: =IF($H14="","",IF($H14>=6,"High",IF($H14>=3,"Medium","Low"))) | J14: Make the RTM update part of the definition of done for a controlled artefact and require the affected IDs in the pull request template. Treat identifiers as permanent — retire an entry as Withdrawn rather than reusing its number, which matters most if RSK-006 is ever realised. | K14: Reconstruct the trace from pull request history, re-review it, and record the gap in the version history rather than back-dating entries. | L14: Robert | M14: Open — mitigated | N14: CON-001 · RTM · RSK-006 · Master Brief s.11 | O14: Mitigated, not closed. DEC-011 accepted that no single location states what a transition does; bounded by the single subscription registry (src/events/subscribers/index.js, listSubscriptions() asserted by test). RTM extended to v0.5; the pull request template (#53) will require the affected IDs. Residual: a merged change that skips the RTM update.
... B23: RSK-021 | C23: An attacker guesses a user's password through POST /api/v1/sessions, because login has no throttling or lockout, and acts on requests with that user's roles. | D23: DEC-018 deliberately sets no throttling or lockout threshold: the record states no figure, and choosing one would invent a value. The only rate limit is the scrypt cost per process. The record also states no password-strength requirement. | E23: Repeated auth.login.failure events in auditLog for one account or one source within minutes; CON-019 adversarial testing targeting login; any successful login following a run of failures. | F23: 2 | G23: 3 | H23: =F23*G23 | I23: =IF($H23="","",IF($H23>=6,"High",IF($H23>=3,"Medium","Low"))) | J23: Slow scrypt hash caps guesses per process (DEC-018 §2). Identical 401 and a dummy hash for unknown emails, so accounts cannot be enumerated. Every attempt is logged (NFR-1.4). Any control the team adopts must come with a figure from a defensible source (for example OWASP ASVS) and be recorded as a DEC. | K23: Revoke the affected account (FR-1.4 epoch terminates its sessions); review its auditLog trail; adopt a throttling control through a DEC. Weigh account lockout carefully: a lockout threshold gives an attacker a lever to deny service to real users by deliberately failing their logins, so per-source throttling or progressive delay may be preferable to per-account lockout. | L23: Ethan | M23: Open | N23: DEC-018 · NFR-1.4 · NFR-3.1 · CON-019 · CON-006 · FR-1.4 | O23: New at M3 — raised by DEC-018 (11/10/2026). Score proposed by the drafter, to be confirmed by the owner.

Sheet Defence Prep
B1: 8.3 Highest-priority risk — defence
B4: Aspect | C4: Response
B5: Risk | C5: RSK-001 — Requesters keep using email, telephone and WhatsApp after the platform is live, so the single controlled record of a request lifecycle is never achieved. Priority 9 (High).
B6: Why it deserves the most attention now | C6: Two risks score 9, so the score does not settle it. RSK-002 (indefinite retention of personal information) is serious, but it is inside our control: DEC-005 is already open with a named evidence requirement, and the remedy is a rule we can apply once STK-009 supplies it. RSK-001 is different in kind. The platform can satisfy every requirement we baseline and still fail, because the business need in s.2.1 is a single controlled record and that depends on the organisation retiring channels the system does not own. It is also the risk the team deliberately took on: SCP-017 excludes ingestion from the existing channels for a sound engineering reason — federating them would preserve the duplication we exist to remove — and that correct decision is precisely what leaves adoption as the exposure. A risk created by our own reasoned choice is the one we are most accountable for.
B7: Requirements and constraints threatened | C7: The business need behind the whole scope baseline; SCP-001 and SCP-003 (submission and status visibility, which only work if requests arrive here); SCP-011, whose management reporting is only as complete as the data captured — if requests arrive off-platform, that requirement is unverifiable however well it is built. STK-001, STK-004 and STK-005 all lose value; STK-008 loses the accountability improvement that justified funding it.
B8: Early-warning indicator | C8: Any pilot week in which STK-004 reports requests still arriving by telephone or WhatsApp. Chosen because it is observable during M3 by the one stakeholder who sees every channel, rather than a lagging measure such as final adoption at M4.
B9: Mitigation already in place | C9: SCP-017 defends the exclusion on engineering grounds rather than leaving it unexamined. Channel retirement is recorded as an assumption with its impact if invalid rather than assumed silently. SCP-001 is written so that STK-004 can capture a request on a requester's behalf, so contacts arriving informally still enter the controlled record. [Cite the issue or PR reference as evidence.]
B10: Consequence if unmitigated | C10: The platform becomes a fourth channel alongside the three that already exist. Duplication and lost requests continue, and management reporting is drawn from partial data — which is worse than no reporting, because it looks authoritative. At M4 the team would have to report that the delivered system satisfied its requirements but not the stakeholder need, which is exactly the distinction the module assesses.
B12: Defence question 6 — why later-lifecycle concerns belong in M1 | C12: See §9.3 on the PED Text tab. Short form: recording a concern preserves options, deciding it now on insufficient evidence closes them. The test is whether the baseline is different because of it — the FEC Influence tab names the differences, and most of them are already visible in A's registers.
B13: Defence question 7 — a decision deliberately not made | C13: Three are open in A's log. The strongest to defend is DEC-003 (hosting platform), because the reason for deferring is a genuine conflict between constraints — CON-003 favours a free tier while CON-006 and CON-007 need audit retention and backup that free tiers often omit — and the evidence required is named and obtainable. DEC-005 (retention) is the one with the most downstream consequence.
B14: Defence question 12 — an early shortcut that creates debt later | C14: Treating authorisation as an application-level concern instead of an architecturally significant one. DEC-004 explicitly rejected that shortcut. It is the fastest route to a working system and the most expensive to unpick, because authorisation cuts across every view, query, transition and test written after it — which is why it is recorded as a decision rather than left to construction.
B15: A gap to raise honestly, not hide | C15: No decision or deferment has been logged for the SCP-011 service-level target, although every other open question in the baseline is captured as a DEC. Carried here as RSK-003. Raising it yourself in the presentation is stronger evidence of control than being asked about it.
